setup.py
delayrq/__init__.py
delayrq/lock.py
delayrq/queue.py
delayrq/timer.py
delayrq.egg-info/PKG-INFO
delayrq.egg-info/SOURCES.txt
delayrq.egg-info/dependency_links.txt
delayrq.egg-info/requires.txt
delayrq.egg-info/top_level.txt