Metadata-Version: 1.0
Name: delayrq
Version: 0.1.0
Summary: A delayed queues for RQ
Home-page: http://github.com/cocoakekeyu/delay-rq
Author: cocoakekeyu
Author-email: cocoakekeyu@gmail.com
License: MIT
Platform: all
